{
  "hash": "1a2f625e",
  "configHash": "9b49ecec",
  "lockfileHash": "9180c3d6",
  "browserHash": "3a4331f5",
  "optimized": {
    "vue": {
      "src": "../../../../node_modules/vue/dist/vue.runtime.esm-bundler.js",
      "file": "vue.js",
      "fileHash": "7b1c9dad",
      "needsInterop": false
    },
    "vitepress > @vue/devtools-api": {
      "src": "../../../../node_modules/@vue/devtools-api/dist/index.js",
      "file": "vitepress___@vue_devtools-api.js",
      "fileHash": "ee1139c1",
      "needsInterop": false
    },
    "vitepress > @vueuse/core": {
      "src": "../../../../node_modules/@vueuse/core/index.mjs",
      "file": "vitepress___@vueuse_core.js",
      "fileHash": "f036bd0c",
      "needsInterop": false
    },
    "@theme/index": {
      "src": "../../../../node_modules/vitepress/dist/client/theme-default/index.js",
      "file": "@theme_index.js",
      "fileHash": "7db6a94b",
      "needsInterop": false
    }
  },
  "chunks": {
    "chunk-BRNHR3LR": {
      "file": "chunk-BRNHR3LR.js"
    },
    "chunk-H6MPEGKE": {
      "file": "chunk-H6MPEGKE.js"
    }
  }
}